<manifest alg="2" build="2018.1.0.386" opt="true" iceEnabled="false" exportTarget="other" domain="www.wienerblut.org,www.nikomi.de" resolutions="1x" timestamp="1535797936978">
  <folder name="css">
    <file name="site_global.css" crc="288436422"/>
    <file name="drinks.css" crc="4164643967" ref="drinks"/>
    <file name="nomq_drinks.css" crc="3889138073" ref="drinks"/>
    <file name="index.css" crc="4057100490" ref="index"/>
    <file name="nomq_index.css" crc="4233071020" ref="index"/>
    <file name="sounds.css" crc="3774817579" ref="sounds"/>
    <file name="nomq_sounds.css" crc="4017574502" ref="sounds"/>
    <file name="events.css" crc="4284486749" ref="events"/>
    <file name="nomq_events.css" crc="326598578" ref="events"/>
    <file name="history.css" crc="93882787" ref="history"/>
    <file name="nomq_history.css" crc="4046344216" ref="history"/>
    <file name="galerie.css" crc="149040900" ref="galerie"/>
    <file name="nomq_galerie.css" crc="3761441853" ref="galerie"/>
    <file name="impressum.css" crc="410565013" ref="impressum"/>
    <file name="nomq_impressum.css" crc="323072188" ref="impressum"/>
  </folder>
  <folder name="scripts">
    <file name="jquery-1.8.3.min.js" crc="209076791" ref="index:events:sounds:drinks:history:galerie:impressum"/>
    <file name="museutils.js" crc="340535759" ref="index:events:sounds:drinks:history:galerie:impressum"/>
    <file name="whatinput.js" crc="86476730" ref="index:events:sounds:drinks:history:galerie:impressum"/>
    <file name="museconfig.js" crc="310584261" ref="index:events:sounds:drinks:history:galerie:impressum"/>
    <file name="jquery.musepolyfill.bgsize.js" crc="4260645839" ref="index:events:sounds:drinks:history:galerie:impressum"/>
    <file name="webpro.js" crc="4059564322" ref="index:events:sounds:drinks:history:galerie:impressum"/>
    <file name="musewpdisclosure.js" crc="3883500470" ref="index:events:sounds:drinks:history:galerie:impressum"/>
    <file name="jquery.scrolleffects.js" crc="39568856" ref="index:events:sounds:drinks:history:galerie:impressum"/>
    <file name="jquery.museresponsive.js" crc="527716135" ref="index:events:sounds:drinks:history:galerie:impressum"/>
    <file name="require.js" crc="7928878" ref="index:events:sounds:drinks:history:galerie:impressum"/>
  </folder>
  <folder name="images">
    <file name="bg.jpg" crc="4245234804" ref="index:events:sounds:drinks:history:galerie:impressum">
      <caption webpage="index" alt=""/>
      <caption webpage="drinks" alt=""/>
      <caption webpage="galerie" alt=""/>
      <caption webpage="sounds" alt=""/>
    </file>
    <file name="menuburger.png" crc="4234233567" ref="index:events:sounds:drinks:history:galerie:impressum">
      <caption webpage="drinks" alt=""/>
      <caption webpage="drinks" alt=""/>
      <caption webpage="drinks" alt=""/>
      <caption webpage="drinks" alt=""/>
      <caption webpage="events" alt=""/>
      <caption webpage="events" alt=""/>
      <caption webpage="events" alt=""/>
      <caption webpage="events" alt=""/>
      <caption webpage="galerie" alt=""/>
      <caption webpage="galerie" alt=""/>
      <caption webpage="galerie" alt=""/>
      <caption webpage="galerie" alt=""/>
      <caption webpage="history" alt=""/>
      <caption webpage="history" alt=""/>
      <caption webpage="history" alt=""/>
      <caption webpage="history" alt=""/>
      <caption webpage="index" alt=""/>
      <caption webpage="index" alt=""/>
      <caption webpage="index" alt=""/>
      <caption webpage="index" alt=""/>
      <caption webpage="impressum" alt=""/>
      <caption webpage="impressum" alt=""/>
      <caption webpage="impressum" alt=""/>
      <caption webpage="impressum" alt=""/>
      <caption webpage="sounds" alt=""/>
      <caption webpage="sounds" alt=""/>
      <caption webpage="sounds" alt=""/>
      <caption webpage="sounds" alt=""/>
    </file>
    <file name="menux.png" crc="408645707" ref="index:events:sounds:drinks:history:galerie:impressum">
      <caption webpage="drinks" alt=""/>
      <caption webpage="drinks" alt=""/>
      <caption webpage="drinks" alt=""/>
      <caption webpage="drinks" alt=""/>
      <caption webpage="events" alt=""/>
      <caption webpage="events" alt=""/>
      <caption webpage="events" alt=""/>
      <caption webpage="events" alt=""/>
      <caption webpage="galerie" alt=""/>
      <caption webpage="galerie" alt=""/>
      <caption webpage="galerie" alt=""/>
      <caption webpage="galerie" alt=""/>
      <caption webpage="history" alt=""/>
      <caption webpage="history" alt=""/>
      <caption webpage="history" alt=""/>
      <caption webpage="history" alt=""/>
      <caption webpage="index" alt=""/>
      <caption webpage="index" alt=""/>
      <caption webpage="index" alt=""/>
      <caption webpage="index" alt=""/>
      <caption webpage="impressum" alt=""/>
      <caption webpage="impressum" alt=""/>
      <caption webpage="impressum" alt=""/>
      <caption webpage="impressum" alt=""/>
      <caption webpage="sounds" alt=""/>
      <caption webpage="sounds" alt=""/>
      <caption webpage="sounds" alt=""/>
      <caption webpage="sounds" alt=""/>
    </file>
    <file name="svg-79263x50.svg" crc="3776745767" seo="true" ref="index:events:sounds:drinks:history:galerie:impressum">
      <caption webpage="drinks" alt=""/>
      <caption webpage="drinks" alt=""/>
      <caption webpage="drinks" alt=""/>
      <caption webpage="drinks" alt=""/>
      <caption webpage="events" alt=""/>
      <caption webpage="events" alt=""/>
      <caption webpage="events" alt=""/>
      <caption webpage="events" alt=""/>
      <caption webpage="galerie" alt=""/>
      <caption webpage="galerie" alt=""/>
      <caption webpage="galerie" alt=""/>
      <caption webpage="galerie" alt=""/>
      <caption webpage="history" alt=""/>
      <caption webpage="history" alt=""/>
      <caption webpage="history" alt=""/>
      <caption webpage="history" alt=""/>
      <caption webpage="index" alt=""/>
      <caption webpage="index" alt=""/>
      <caption webpage="index" alt=""/>
      <caption webpage="index" alt=""/>
      <caption webpage="impressum" alt=""/>
      <caption webpage="impressum" alt=""/>
      <caption webpage="impressum" alt=""/>
      <caption webpage="impressum" alt=""/>
      <caption webpage="sounds" alt=""/>
      <caption webpage="sounds" alt=""/>
      <caption webpage="sounds" alt=""/>
      <caption webpage="sounds" alt=""/>
    </file>
    <file name="svg 79263x50_poster_.png" crc="420175556" ref="index"/>
    <file name="pasted-svg-723x723.svg" crc="439312057" seo="true" ref="index:events:sounds:drinks:history:galerie:impressum">
      <caption webpage="drinks" alt=""/>
      <caption webpage="drinks" alt=""/>
      <caption webpage="drinks" alt=""/>
      <caption webpage="drinks" alt=""/>
      <caption webpage="events" alt=""/>
      <caption webpage="events" alt=""/>
      <caption webpage="events" alt=""/>
      <caption webpage="events" alt=""/>
      <caption webpage="galerie" alt=""/>
      <caption webpage="galerie" alt=""/>
      <caption webpage="galerie" alt=""/>
      <caption webpage="galerie" alt=""/>
      <caption webpage="history" alt=""/>
      <caption webpage="history" alt=""/>
      <caption webpage="history" alt=""/>
      <caption webpage="history" alt=""/>
      <caption webpage="index" alt=""/>
      <caption webpage="index" alt=""/>
      <caption webpage="index" alt=""/>
      <caption webpage="index" alt=""/>
      <caption webpage="impressum" alt=""/>
      <caption webpage="impressum" alt=""/>
      <caption webpage="impressum" alt=""/>
      <caption webpage="impressum" alt=""/>
      <caption webpage="sounds" alt=""/>
      <caption webpage="sounds" alt=""/>
      <caption webpage="sounds" alt=""/>
      <caption webpage="sounds" alt=""/>
    </file>
    <file name="pasted svg 723x723_poster_.png" crc="437880860" ref="index"/>
    <file name="bar2.jpg" crc="4113480769" ref="index:events:sounds:drinks:history:galerie:impressum">
      <caption webpage="index" alt=""/>
      <caption webpage="drinks" alt=""/>
      <caption webpage="galerie" alt=""/>
      <caption webpage="sounds" alt=""/>
    </file>
    <file name="brett-u29249-fr.jpg" crc="347021797" ref="index:events:history:drinks:sounds:galerie:impressum"/>
    <file name="blood-drop.svg" crc="4069286476" seo="true" ref="index:events:sounds:drinks:history:galerie:impressum">
      <caption webpage="drinks" alt=""/>
      <caption webpage="drinks" alt=""/>
      <caption webpage="drinks" alt=""/>
      <caption webpage="drinks" alt=""/>
      <caption webpage="drinks" alt=""/>
      <caption webpage="events" alt=""/>
      <caption webpage="events" alt=""/>
      <caption webpage="events" alt=""/>
      <caption webpage="events" alt=""/>
      <caption webpage="events" alt=""/>
      <caption webpage="galerie" alt=""/>
      <caption webpage="galerie" alt=""/>
      <caption webpage="galerie" alt=""/>
      <caption webpage="galerie" alt=""/>
      <caption webpage="galerie" alt=""/>
      <caption webpage="history" alt=""/>
      <caption webpage="history" alt=""/>
      <caption webpage="history" alt=""/>
      <caption webpage="history" alt=""/>
      <caption webpage="history" alt=""/>
      <caption webpage="index" alt=""/>
      <caption webpage="index" alt=""/>
      <caption webpage="index" alt=""/>
      <caption webpage="index" alt=""/>
      <caption webpage="index" alt=""/>
      <caption webpage="index" alt=""/>
      <caption webpage="impressum" alt=""/>
      <caption webpage="impressum" alt=""/>
      <caption webpage="impressum" alt=""/>
      <caption webpage="impressum" alt=""/>
      <caption webpage="impressum" alt=""/>
      <caption webpage="sounds" alt=""/>
      <caption webpage="sounds" alt=""/>
      <caption webpage="sounds" alt=""/>
      <caption webpage="sounds" alt=""/>
      <caption webpage="sounds" alt=""/>
    </file>
    <file name="blood-drop_poster_.png" crc="4166989775" ref="index"/>
    <file name="pasted-svg-39082x19.svg" crc="4280401314" seo="true" ref="index:events:sounds:drinks:history:galerie:impressum">
      <caption webpage="drinks" alt=""/>
      <caption webpage="drinks" alt=""/>
      <caption webpage="drinks" alt=""/>
      <caption webpage="drinks" alt=""/>
      <caption webpage="drinks" alt=""/>
      <caption webpage="events" alt=""/>
      <caption webpage="events" alt=""/>
      <caption webpage="events" alt=""/>
      <caption webpage="events" alt=""/>
      <caption webpage="events" alt=""/>
      <caption webpage="galerie" alt=""/>
      <caption webpage="galerie" alt=""/>
      <caption webpage="galerie" alt=""/>
      <caption webpage="galerie" alt=""/>
      <caption webpage="galerie" alt=""/>
      <caption webpage="history" alt=""/>
      <caption webpage="history" alt=""/>
      <caption webpage="history" alt=""/>
      <caption webpage="history" alt=""/>
      <caption webpage="history" alt=""/>
      <caption webpage="index" alt=""/>
      <caption webpage="index" alt=""/>
      <caption webpage="index" alt=""/>
      <caption webpage="index" alt=""/>
      <caption webpage="index" alt=""/>
      <caption webpage="index" alt=""/>
      <caption webpage="impressum" alt=""/>
      <caption webpage="impressum" alt=""/>
      <caption webpage="impressum" alt=""/>
      <caption webpage="impressum" alt=""/>
      <caption webpage="impressum" alt=""/>
      <caption webpage="sounds" alt=""/>
      <caption webpage="sounds" alt=""/>
      <caption webpage="sounds" alt=""/>
      <caption webpage="sounds" alt=""/>
      <caption webpage="sounds" alt=""/>
    </file>
    <file name="pasted svg 39082x19_poster_.png" crc="51450954" ref="index"/>
    <file name="logo276x277.png" crc="3819452922" seo="true" ref="index">
      <caption webpage="index" alt=""/>
      <caption webpage="index" alt=""/>
      <caption webpage="index" alt=""/>
      <caption webpage="drinks" alt=""/>
      <caption webpage="drinks" alt=""/>
      <caption webpage="galerie" alt=""/>
      <caption webpage="galerie" alt=""/>
      <caption webpage="sounds" alt=""/>
      <caption webpage="sounds" alt=""/>
    </file>
    <file name="u30087-9-a.png" crc="3954508339" ref="index"/>
    <file name="u30087-9-a2.png" crc="3954508339" ref="index"/>
    <file name="brett.jpg" crc="4227349727" ref="index:events:sounds:drinks:history:galerie:impressum">
      <caption webpage="drinks" alt=""/>
      <caption webpage="drinks" alt=""/>
      <caption webpage="drinks" alt=""/>
      <caption webpage="events" alt=""/>
      <caption webpage="events" alt=""/>
      <caption webpage="events" alt=""/>
      <caption webpage="galerie" alt=""/>
      <caption webpage="galerie" alt=""/>
      <caption webpage="galerie" alt=""/>
      <caption webpage="history" alt=""/>
      <caption webpage="history" alt=""/>
      <caption webpage="history" alt=""/>
      <caption webpage="index" alt=""/>
      <caption webpage="index" alt=""/>
      <caption webpage="index" alt=""/>
      <caption webpage="impressum" alt=""/>
      <caption webpage="impressum" alt=""/>
      <caption webpage="impressum" alt=""/>
      <caption webpage="sounds" alt=""/>
      <caption webpage="sounds" alt=""/>
      <caption webpage="sounds" alt=""/>
    </file>
    <file name="u30087-9-a3.png" crc="3896333092" ref="index"/>
    <file name="u30087-9-a4.png" crc="4112209938" ref="index"/>
    <file name="u30087-9-a5.png" crc="4112209938" ref="index"/>
    <file name="u30087-9-a6.png" crc="4279727872" ref="index"/>
    <file name="brett-u29249-fr2.jpg" crc="208210498" ref="index:events:history:drinks:sounds:galerie:impressum"/>
    <file name="bg-u28943-fr.jpg" crc="3958265412" ref="index"/>
    <file name="blank.gif" crc="4208392903" ref="index:events:sounds:drinks:history:galerie:impressum"/>
    <file name="polaroid-blank.jpg" crc="4280349780" seo="true" ref="events">
      <caption webpage="events" alt=""/>
    </file>
    <file name="instagram.png" crc="4023951650" seo="true" ref="events">
      <caption webpage="events" alt=""/>
      <caption webpage="events" alt=""/>
      <caption webpage="events" alt=""/>
      <caption webpage="events" alt=""/>
      <caption webpage="events" alt=""/>
      <caption webpage="events" alt=""/>
    </file>
    <file name="vizediktator.jpg" crc="508947516" ref="events">
      <caption webpage="events" alt=""/>
    </file>
    <file name="u31301-9.png" crc="3954508339" ref="events"/>
    <file name="u31301-92.png" crc="3954508339" ref="events"/>
    <file name="u31301-93.png" crc="3896333092" ref="events"/>
    <file name="u31301-94.png" crc="4112209938" ref="events"/>
    <file name="u31301-95.png" crc="4112209938" ref="events"/>
    <file name="u31301-96.png" crc="4279727872" ref="events"/>
    <file name="10846419_10203478986199741_5055703376206504338_n.jpg" crc="4075302696" ref="sounds">
      <caption webpage="sounds" alt=""/>
    </file>
    <file name="u32989-9.png" crc="3954508339" ref="sounds"/>
    <file name="u32989-92.png" crc="3954508339" ref="sounds"/>
    <file name="u32989-93.png" crc="3896333092" ref="sounds"/>
    <file name="u32989-94.png" crc="4112209938" ref="sounds"/>
    <file name="u32989-95.png" crc="4112209938" ref="sounds"/>
    <file name="u32989-96.png" crc="4279727872" ref="sounds"/>
    <file name="68086_3725924431115_711321469_n.jpg" crc="3957475837" ref="drinks:galerie">
      <caption webpage="drinks" alt=""/>
      <caption webpage="galerie" alt=""/>
    </file>
    <file name="u35483-9.png" crc="3954508339" ref="drinks"/>
    <file name="bier.jpg" crc="4027412953" seo="true" ref="drinks:galerie">
      <caption webpage="drinks" alt=""/>
      <caption webpage="drinks" alt=""/>
      <caption webpage="drinks" alt=""/>
      <caption webpage="drinks" alt=""/>
      <caption webpage="drinks" alt=""/>
      <caption webpage="drinks" alt=""/>
      <caption webpage="galerie" alt=""/>
      <caption webpage="galerie" alt=""/>
      <caption webpage="galerie" alt=""/>
      <caption webpage="galerie" alt=""/>
      <caption webpage="galerie" alt=""/>
    </file>
    <file name="spezi.jpg" crc="3977154899" seo="true" ref="drinks:galerie">
      <caption webpage="drinks" alt=""/>
      <caption webpage="drinks" alt=""/>
      <caption webpage="drinks" alt=""/>
      <caption webpage="drinks" alt=""/>
      <caption webpage="drinks" alt=""/>
      <caption webpage="drinks" alt=""/>
      <caption webpage="galerie" alt=""/>
      <caption webpage="galerie" alt=""/>
      <caption webpage="galerie" alt=""/>
      <caption webpage="galerie" alt=""/>
      <caption webpage="galerie" alt=""/>
    </file>
    <file name="sekt.jpg" crc="54190253" seo="true" ref="drinks:galerie">
      <caption webpage="drinks" alt=""/>
      <caption webpage="drinks" alt=""/>
      <caption webpage="drinks" alt=""/>
      <caption webpage="drinks" alt=""/>
      <caption webpage="drinks" alt=""/>
      <caption webpage="drinks" alt=""/>
      <caption webpage="galerie" alt=""/>
      <caption webpage="galerie" alt=""/>
      <caption webpage="galerie" alt=""/>
      <caption webpage="galerie" alt=""/>
      <caption webpage="galerie" alt=""/>
    </file>
    <file name="kirschschorle.jpg" crc="4189131366" seo="true" ref="drinks:galerie">
      <caption webpage="drinks" alt=""/>
      <caption webpage="drinks" alt=""/>
      <caption webpage="drinks" alt=""/>
      <caption webpage="drinks" alt=""/>
      <caption webpage="drinks" alt=""/>
      <caption webpage="drinks" alt=""/>
      <caption webpage="galerie" alt=""/>
      <caption webpage="galerie" alt=""/>
      <caption webpage="galerie" alt=""/>
      <caption webpage="galerie" alt=""/>
      <caption webpage="galerie" alt=""/>
    </file>
    <file name="moscowmule.jpg" crc="3982512820" seo="true" ref="drinks:galerie">
      <caption webpage="drinks" alt=""/>
      <caption webpage="drinks" alt=""/>
      <caption webpage="drinks" alt=""/>
      <caption webpage="drinks" alt=""/>
      <caption webpage="drinks" alt=""/>
      <caption webpage="drinks" alt=""/>
      <caption webpage="galerie" alt=""/>
      <caption webpage="galerie" alt=""/>
      <caption webpage="galerie" alt=""/>
      <caption webpage="galerie" alt=""/>
      <caption webpage="galerie" alt=""/>
    </file>
    <file name="cocktail.jpg" crc="310944177" seo="true" ref="drinks:galerie">
      <caption webpage="drinks" alt=""/>
      <caption webpage="drinks" alt=""/>
      <caption webpage="drinks" alt=""/>
      <caption webpage="drinks" alt=""/>
      <caption webpage="drinks" alt=""/>
      <caption webpage="drinks" alt=""/>
      <caption webpage="galerie" alt=""/>
      <caption webpage="galerie" alt=""/>
      <caption webpage="galerie" alt=""/>
      <caption webpage="galerie" alt=""/>
      <caption webpage="galerie" alt=""/>
    </file>
    <file name="u35483-92.png" crc="3954508339" ref="drinks"/>
    <file name="u35483-93.png" crc="3896333092" ref="drinks"/>
    <file name="u35483-94.png" crc="4112209938" ref="drinks"/>
    <file name="u35483-95.png" crc="4112209938" ref="drinks"/>
    <file name="u35483-96.png" crc="4279727872" ref="drinks"/>
    <file name="cops.jpg" crc="307987777" seo="true" ref="drinks:galerie">
      <caption webpage="drinks" alt=""/>
      <caption webpage="drinks" alt=""/>
      <caption webpage="drinks" alt=""/>
      <caption webpage="drinks" alt=""/>
      <caption webpage="drinks" alt=""/>
      <caption webpage="drinks" alt=""/>
      <caption webpage="galerie" alt=""/>
      <caption webpage="galerie" alt=""/>
      <caption webpage="galerie" alt=""/>
      <caption webpage="galerie" alt=""/>
      <caption webpage="galerie" alt=""/>
    </file>
    <file name="schnaps3.jpg" crc="503290245" seo="true" ref="drinks:galerie">
      <caption webpage="drinks" alt=""/>
      <caption webpage="drinks" alt=""/>
      <caption webpage="drinks" alt=""/>
      <caption webpage="drinks" alt=""/>
      <caption webpage="drinks" alt=""/>
      <caption webpage="drinks" alt=""/>
      <caption webpage="galerie" alt=""/>
      <caption webpage="galerie" alt=""/>
      <caption webpage="galerie" alt=""/>
      <caption webpage="galerie" alt=""/>
      <caption webpage="galerie" alt=""/>
    </file>
    <file name="schnaps5.jpg" crc="4034173810" seo="true" ref="drinks:galerie">
      <caption webpage="drinks" alt=""/>
      <caption webpage="drinks" alt=""/>
      <caption webpage="drinks" alt=""/>
      <caption webpage="drinks" alt=""/>
      <caption webpage="drinks" alt=""/>
      <caption webpage="drinks" alt=""/>
      <caption webpage="galerie" alt=""/>
      <caption webpage="galerie" alt=""/>
      <caption webpage="galerie" alt=""/>
      <caption webpage="galerie" alt=""/>
      <caption webpage="galerie" alt=""/>
    </file>
    <file name="jazz.jpg" crc="4153315819" ref="history">
      <caption webpage="history" alt=""/>
    </file>
    <file name="u39811-9.png" crc="3954508339" ref="history"/>
    <file name="u39811-92.png" crc="3954508339" ref="history"/>
    <file name="u39811-93.png" crc="3896333092" ref="history"/>
    <file name="u39811-94.png" crc="4112209938" ref="history"/>
    <file name="u39811-95.png" crc="4112209938" ref="history"/>
    <file name="u39811-96.png" crc="4279727872" ref="history"/>
    <file name="polaroid-blank274x321.jpg" crc="4201281644" seo="true" ref="events">
      <caption webpage="events" alt=""/>
      <caption webpage="events" alt=""/>
      <caption webpage="events" alt=""/>
      <caption webpage="events" alt=""/>
      <caption webpage="events" alt=""/>
    </file>
    <file name="u42680-9.png" crc="3954508339" ref="galerie"/>
    <file name="dsc00197.jpg" crc="144202982" seo="true" ref="galerie">
      <caption webpage="galerie" alt=""/>
      <caption webpage="galerie" alt=""/>
      <caption webpage="galerie" alt=""/>
      <caption webpage="galerie" alt=""/>
      <caption webpage="galerie" alt=""/>
      <caption webpage="galerie" alt=""/>
    </file>
    <file name="dsc01665.jpg" crc="4189295033" seo="true" ref="galerie">
      <caption webpage="galerie" alt=""/>
      <caption webpage="galerie" alt=""/>
      <caption webpage="galerie" alt=""/>
      <caption webpage="galerie" alt=""/>
      <caption webpage="galerie" alt=""/>
      <caption webpage="galerie" alt=""/>
    </file>
    <file name="dsc01666.jpg" crc="4157972878" seo="true" ref="galerie">
      <caption webpage="galerie" alt=""/>
      <caption webpage="galerie" alt=""/>
      <caption webpage="galerie" alt=""/>
      <caption webpage="galerie" alt=""/>
      <caption webpage="galerie" alt=""/>
      <caption webpage="galerie" alt=""/>
    </file>
    <file name="dsc02018.jpg" crc="4010507281" seo="true" ref="galerie">
      <caption webpage="galerie" alt=""/>
      <caption webpage="galerie" alt=""/>
      <caption webpage="galerie" alt=""/>
      <caption webpage="galerie" alt=""/>
      <caption webpage="galerie" alt=""/>
      <caption webpage="galerie" alt=""/>
    </file>
    <file name="dsc02064.jpg" crc="440002181" seo="true" ref="galerie">
      <caption webpage="galerie" alt=""/>
      <caption webpage="galerie" alt=""/>
      <caption webpage="galerie" alt=""/>
      <caption webpage="galerie" alt=""/>
      <caption webpage="galerie" alt=""/>
      <caption webpage="galerie" alt=""/>
    </file>
    <file name="dsc08207.jpg" crc="3866112256" seo="true" ref="galerie">
      <caption webpage="galerie" alt=""/>
      <caption webpage="galerie" alt=""/>
      <caption webpage="galerie" alt=""/>
      <caption webpage="galerie" alt=""/>
      <caption webpage="galerie" alt=""/>
      <caption webpage="galerie" alt=""/>
    </file>
    <file name="dsc08210.jpg" crc="360008402" seo="true" ref="galerie">
      <caption webpage="galerie" alt=""/>
      <caption webpage="galerie" alt=""/>
      <caption webpage="galerie" alt=""/>
      <caption webpage="galerie" alt=""/>
      <caption webpage="galerie" alt=""/>
      <caption webpage="galerie" alt=""/>
    </file>
    <file name="dsc08263.jpg" crc="4021466672" seo="true" ref="galerie">
      <caption webpage="galerie" alt=""/>
      <caption webpage="galerie" alt=""/>
      <caption webpage="galerie" alt=""/>
      <caption webpage="galerie" alt=""/>
      <caption webpage="galerie" alt=""/>
      <caption webpage="galerie" alt=""/>
    </file>
    <file name="dsc08272.jpg" crc="3864119649" seo="true" ref="galerie">
      <caption webpage="galerie" alt=""/>
      <caption webpage="galerie" alt=""/>
      <caption webpage="galerie" alt=""/>
      <caption webpage="galerie" alt=""/>
      <caption webpage="galerie" alt=""/>
      <caption webpage="galerie" alt=""/>
    </file>
    <file name="dsc08359.jpg" crc="353534587" seo="true" ref="galerie">
      <caption webpage="galerie" alt=""/>
      <caption webpage="galerie" alt=""/>
      <caption webpage="galerie" alt=""/>
      <caption webpage="galerie" alt=""/>
      <caption webpage="galerie" alt=""/>
      <caption webpage="galerie" alt=""/>
    </file>
    <file name="dsc08420.jpg" crc="487874422" seo="true" ref="galerie">
      <caption webpage="galerie" alt=""/>
      <caption webpage="galerie" alt=""/>
      <caption webpage="galerie" alt=""/>
      <caption webpage="galerie" alt=""/>
      <caption webpage="galerie" alt=""/>
      <caption webpage="galerie" alt=""/>
    </file>
    <file name="u42680-92.png" crc="3954508339" ref="galerie"/>
    <file name="u42680-93.png" crc="3896333092" ref="galerie"/>
    <file name="u42680-94.png" crc="4112209938" ref="galerie"/>
    <file name="u42680-95.png" crc="4112209938" ref="galerie"/>
    <file name="u42680-96.png" crc="4279727872" ref="galerie"/>
    <file name="tanzflaeche.jpg" crc="4178716705" ref="galerie">
      <caption webpage="galerie" alt=""/>
    </file>
    <file name="u51120-9.png" crc="3954508339" ref="impressum"/>
    <file name="u51120-92.png" crc="3954508339" ref="impressum"/>
    <file name="u51120-93.png" crc="3896333092" ref="impressum"/>
    <file name="u51120-94.png" crc="4112209938" ref="impressum"/>
    <file name="u51120-95.png" crc="4112209938" ref="impressum"/>
    <file name="u51120-96.png" crc="4279727872" ref="impressum"/>
  </folder>
  <file name="index.html" crc="3771246929" seo="true" mt="1535797567291" redirect="true"/>
  <file name="events.html" crc="3891975682" seo="true" mt="1535797642443" redirect="true"/>
  <file name="sounds.html" crc="3823330617" seo="true" mt="1535797664845" redirect="true"/>
  <file name="drinks.html" crc="4266259136" seo="true" mt="1535797698716" redirect="true"/>
  <file name="history.html" crc="22289241" seo="true" mt="1535797735992" redirect="true"/>
  <file name="galerie.html" crc="34901621" seo="true" mt="1535797716656" redirect="true"/>
  <file name="impressum.html" crc="3904188367" seo="true" mt="1535797544147" redirect="true"/>
</manifest>